sockert_exmpl/__init__.py
sockert_exmpl-0.1.0.dist-info/WHEEL
sockert_exmpl-0.1.0.dist-info/METADATA
sockert_exmpl-0.1.0.dist-info/RECORD
