Metadata-Version: 2.1
Name: sockert-exmpl
Version: 0.1.0
Summary: 
Author: talel-khairi kchih
Author-email: talelkhairi.kchih@celadodc-rswl.com
Requires-Python: >=3.10,<4.0
Classifier: Programming Language :: Python :: 3
Classifier: Programming Language :: Python :: 3.10
Requires-Dist: sockets (>=1.0.0,<2.0.0)
